[
  {
    "商品名称": "Cross-Border Exclusive Dehumidifier Boxes, Household Charcoal-Scented Desiccant from the Source Manufacturer, Wardrobe Moisture-Absorbing Boxes, Oem Specific",
    "商品图链接": "https://cbu01.alicdn.com/O1CN01BKOvRN1E0rl6YxZwz_!!973060290-0-cib.jpg",
    "价格": "¥68.60",
    "供应商名称": "深圳市春旺新材料股份有限公司",
    "发货地": "广东 深圳市龙岗区",
    "发货履约率": "/",
    "回头率": "0%",
    "客服响应率": "96.0%",
    "工厂年限": "23年",
    "源头厂家": "生产型厂家",
    "综合服务分": "5.0",
    "评价数": "53条有内容53条",
    "起订量": "1",
    "近 14 天销量": "7",
    "近 90 天销量": "9",
    "首次上架时间": "2016/04/08",
    "48h 揽收率": "/"
  },
  {
    "商品名称": "Antifreeze Pag -37 ℃ Water Tank Coolant Water Tank Treasure 2kg Fluorescent Yellow Four-Season Universal Type",
    "商品图链接": "https://cbu01.alicdn.com/img/ibank/11881268109_542355256.jpg",
    "价格": "¥55.00",
    "供应商名称": "北京金辉丰奕商贸有限公司",
    "发货地": "北京市",
    "发货履约率": "100.0%",
    "回头率": "100%",
    "客服响应率": "95.0%",
    "工厂年限": "10年",
    "源头厂家": "/",
    "综合服务分": "4.5",
    "评价数": "6条",
    "起订量": "1",
    "近 14 天销量": "1",
    "近 90 天销量": "4",
    "首次上架时间": "2018/08/24",
    "48h 揽收率": "24小时发货"
  },
  {
    "商品名称": "Baisitong Antifreeze -37 ℃ Coolant Domestic Af2100 Fluorescent Yellow 4kg Universal Mixed Type",
    "商品图链接": "https://cbu01.alicdn.com/O1CN01KwqVU72LFiIdmQi2u_!!2926479663-0-cib.jpg",
    "价格": "¥78.00",
    "供应商名称": "北京金辉丰奕商贸有限公司",
    "发货地": "北京市",
    "发货履约率": "50.0%",
    "回头率": "0%",
    "客服响应率": "95.0%",
    "工厂年限": "10年",
    "源头厂家": "/",
    "综合服务分": "4.5",
    "评价数": "10条有内容6条",
    "起订量": "1",
    "近 14 天销量": "1",
    "近 90 天销量": "2",
    "首次上架时间": "2018/08/24",
    "48h 揽收率": "50.0%"
  },
  {
    "商品名称": "Atf Automatic Gearbox Fluid Fully Synthetic Performance Car Engine Oil 5W-40 Engine Automatic Gearbox Transmission Moisture",
    "商品图链接": "https://cbu01.alicdn.com/img/ibank/12648956707_751500691.jpg",
    "价格": "¥89.00",
    "供应商名称": "佛山市南海区里水力度润滑油分装厂",
    "发货地": "广东 佛山市南海区",
    "发货履约率": "/",
    "回头率": "0%",
    "客服响应率": "80.0%",
    "工厂年限": "8年",
    "源头厂家": "/",
    "综合服务分": "4.0",
    "评价数": "41条有内容41条",
    "起订量": "1",
    "近 14 天销量": "/",
    "近 90 天销量": "2",
    "首次上架时间": "2019/09/03",
    "48h 揽收率": "/"
  },
  {
    "商品名称": "Cross-Border Export Anti-Grinder Oil Automatic Transmission Fully Synthetic 4L/1L Car Engine Oil 5W30 Lubricant Motor Oil",
    "商品图链接": "https://cbu01.alicdn.com/img/ibank/11988824127_751500691.jpg",
    "价格": "¥30.00",
    "供应商名称": "佛山市南海区里水力度润滑油分装厂",
    "发货地": "广东 佛山市南海区",
    "发货履约率": "/",
    "回头率": "0%",
    "客服响应率": "80.0%",
    "工厂年限": "8年",
    "源头厂家": "/",
    "综合服务分": "4.0",
    "评价数": "64条有内容64条",
    "起订量": "1",
    "近 14 天销量": "/",
    "近 90 天销量": "2",
    "首次上架时间": "2018/10/11",
    "48h 揽收率": "/"
  },
  {
    "商品名称": "Strong rust remover large barrel 25.00kg steel steel reinforced steel threaded steel industrial metal strong rapid rust removal",
    "商品图链接": "https://cbu01.alicdn.com/O1CN01Q02UGd1o8x43BnUxy_!!2213065335181-0-cib.jpg",
    "价格": "¥120.00",
    "供应商名称": "山东霸克生物科技有限公司",
    "发货地": "山东 滨州市",
    "发货履约率": "100.0%",
    "回头率": "0%",
    "客服响应率": "88.0%",
    "工厂年限": "5年",
    "源头厂家": "/",
    "综合服务分": "4.0",
    "评价数": "/",
    "起订量": "1",
    "近 14 天销量": "2",
    "近 90 天销量": "2",
    "首次上架时间": "2025/04/12",
    "48h 揽收率": "100.0%"
  },
  {
    "商品名称": "Tile Anti-Slip Agent Restaurant Hotel Hot Pot Restaurant Floor Tile Paint Bathroom Toilet Strong Floor Anti-Slip Liquid",
    "商品图链接": "https://cbu01.alicdn.com/O1CN01Y30Sgj1o8x52AVYov_!!2213065335181-0-cib.jpg",
    "价格": "¥230.00",
    "供应商名称": "山东霸克生物科技有限公司",
    "发货地": "山东 滨州市",
    "发货履约率": "100.0%",
    "回头率": "0%",
    "客服响应率": "88.0%",
    "工厂年限": "5年",
    "源头厂家": "/",
    "综合服务分": "4.0",
    "评价数": "/",
    "起订量": "1",
    "近 14 天销量": "1",
    "近 90 天销量": "1",
    "首次上架时间": "2025/06/11",
    "48h 揽收率": "100.0%"
  },
  {
    "商品名称": "Guangdong Manufacturer Supply 18Kg Square Chemical Barrel High Density Seal Environmentally Friendly Materials Variety of Specifications Can Be Printed",
    "商品图链接": "https://cbu01.alicdn.com/img/ibank/1856617996_1230293300.jpg",
    "价格": "¥17.30",
    "供应商名称": "广州市花都区恒辉塑料制品厂(普通合伙)",
    "发货地": "广东 广州市花都区",
    "发货履约率": "/",
    "回头率": "0%",
    "客服响应率": "65.0%",
    "工厂年限": "15年",
    "源头厂家": "/",
    "综合服务分": "4.0",
    "评价数": "/",
    "起订量": "1000",
    "近 14 天销量": "/",
    "近 90 天销量": "/",
    "首次上架时间": "2014/04/26",
    "48h 揽收率": "/"
  },
  {
    "商品名称": "Oxygen underwear laundry detergent manufacturers wholesale cleaning agent underwear mild fragrance cleaning liquid ladies wash a generation of hair",
    "商品图链接": "https://cbu01.alicdn.com/O1CN011UjmbL1TYxPvSDr0D_!!2209586162395-0-cib.jpg",
    "价格": "¥15.41",
    "供应商名称": "民权县晨汐洗涤剂厂",
    "发货地": "河南 商丘市",
    "发货履约率": "/",
    "回头率": "0%",
    "客服响应率": "99.0%",
    "工厂年限": "6年",
    "源头厂家": "/",
    "综合服务分": "4.0",
    "评价数": "/",
    "起订量": "1",
    "近 14 天销量": "/",
    "近 90 天销量": "/",
    "首次上架时间": "2024/01/04",
    "48h 揽收率": "/"
  },
  {
    "商品名称": "Agrifarm Stou Mc 10W-40 Lubricant for Crusher",
    "商品图链接": "https://cbu01.alicdn.com/O1CN0174XJuV1RlCwQ7W6l9_!!2450292151-0-cib.jpg",
    "价格": "¥5000.00",
    "供应商名称": "上海升雄润滑油有限公司",
    "发货地": "上海市松江区",
    "发货履约率": "/",
    "回头率": "0%",
    "客服响应率": "84.0%",
    "工厂年限": "19年",
    "源头厂家": "/",
    "综合服务分": "4.5",
    "评价数": "/",
    "起订量": "3",
    "近 14 天销量": "/",
    "近 90 天销量": "/",
    "首次上架时间": "2025/04/12",
    "48h 揽收率": "/"
  },
  {
    "商品名称": "Agrifarm Stou Mc 10W-40 Lubricant for Crushers",
    "商品图链接": "https://cbu01.alicdn.com/O1CN01WfZqGf1RlCwTTymhs_!!2450292151-0-cib.jpg",
    "价格": "¥1750.00",
    "供应商名称": "上海懋协贸易有限公司",
    "发货地": "上海市静安区",
    "发货履约率": "/",
    "回头率": "0%",
    "客服响应率": "83.0%",
    "工厂年限": "11年",
    "源头厂家": "/",
    "综合服务分": "4.0",
    "评价数": "/",
    "起订量": "3",
    "近 14 天销量": "/",
    "近 90 天销量": "/",
    "首次上架时间": "2021/01/28",
    "48h 揽收率": "/"
  },
  {
    "商品名称": "Cross-border Amazon Dehumidification Box Household Carbon Fragrance Desiccant Wardrobe Aromatic Moisture Absorption Box Chunwang Dehumidification Box",
    "商品图链接": "https://cbu01.alicdn.com/O1CN016GWvJZ1uxECnekDX5_!!2218933426103-0-cib.jpg",
    "价格": "¥98.00",
    "供应商名称": "广州添益电子商务商行(个人独资)",
    "发货地": "广东 广州市",
    "发货履约率": "/",
    "回头率": "0%",
    "客服响应率": "71.0%",
    "工厂年限": "2年",
    "源头厂家": "/",
    "综合服务分": "4.5",
    "评价数": "/",
    "起订量": "1",
    "近 14 天销量": "/",
    "近 90 天销量": "/",
    "首次上架时间": "2024/12/13",
    "48h 揽收率": "/"
  },
  {
    "商品名称": "Cross-border Amazon Dehumidification Box Household Carbon Fragrance Desiccant Wardrobe Aromatic Moisture Absorption Box Chunwang Dehumidification Box",
    "商品图链接": "https://cbu01.alicdn.com/O1CN01BQeMUA1gmK5QXgPCD_!!2217685704184-0-cib.jpg",
    "价格": "¥98.00",
    "供应商名称": "杭州丰品汇日用品有限公司",
    "发货地": "浙江 淳安县",
    "发货履约率": "/",
    "回头率": "0%",
    "客服响应率": "42.0%",
    "工厂年限": "5年",
    "源头厂家": "/",
    "综合服务分": "4.5",
    "评价数": "/",
    "起订量": "1",
    "近 14 天销量": "/",
    "近 90 天销量": "/",
    "首次上架时间": "2024/11/04",
    "48h 揽收率": "/"
  },
  {
    "商品名称": "Cross-border Amazon Dehumidification Box Household Carbon Fragrance Desiccant Wardrobe Aromatic Moisture Absorption Box Chunwang Dehumidification Box",
    "商品图链接": "https://cbu01.alicdn.com/O1CN016GWvJZ1uxECnekDX5_!!2218933426103-0-cib.jpg",
    "价格": "¥98.00",
    "供应商名称": "义乌市毕荣电子商务商行(个体工商户)",
    "发货地": "浙江 金华市",
    "发货履约率": "/",
    "回头率": "0%",
    "客服响应率": "80.0%",
    "工厂年限": "2年",
    "源头厂家": "/",
    "综合服务分": "4.0",
    "评价数": "/",
    "起订量": "1",
    "近 14 天销量": "/",
    "近 90 天销量": "/",
    "首次上架时间": "2025/04/07",
    "48h 揽收率": "/"
  },
  {
    "商品名称": "Antifreeze for Autoglym -37 ℃ Car Water Tank Coolant Water Tank Treasure 2kg Fluorescent Yellow Mixed Type",
    "商品图链接": "https://cbu01.alicdn.com/img/ibank/11873969333_1093916033.jpg",
    "价格": "¥55.00",
    "供应商名称": "北京百川百智科贸有限公司",
    "发货地": "北京市丰台区",
    "发货履约率": "/",
    "回头率": "0%",
    "客服响应率": "96.0%",
    "工厂年限": "12年",
    "源头厂家": "/",
    "综合服务分": "4.5",
    "评价数": "1条",
    "起订量": "2",
    "近 14 天销量": "/",
    "近 90 天销量": "/",
    "首次上架时间": "2018/12/04",
    "48h 揽收率": "/"
  },
  {
    "商品名称": "Baishitong Car Long-Lasting Antifreeze Red Green Color Mixed All-Season Engine Coolant 2kg",
    "商品图链接": "https://cbu01.alicdn.com/img/ibank/12777674584_543493478.jpg",
    "价格": "¥38.00",
    "供应商名称": "北京润天宇商贸有限公司",
    "发货地": "北京市朝阳区",
    "发货履约率": "/",
    "回头率": "0%",
    "客服响应率": "34.0%",
    "工厂年限": "7年",
    "源头厂家": "/",
    "综合服务分": "4.0",
    "评价数": "4条有内容2条",
    "起订量": "2",
    "近 14 天销量": "/",
    "近 90 天销量": "/",
    "首次上架时间": "2019/11/26",
    "48h 揽收率": "/"
  },
  {
    "商品名称": "Baisitong Long-Lasting Antifreeze Coolant Af2100 Fluorescent Yellow Universal Mixed Additive -37 Degrees",
    "商品图链接": "https://cbu01.alicdn.com/O1CN01sCNf8i1q89fy10CZ6_!!1722265450-0-cib.jpg",
    "价格": "¥80.00",
    "供应商名称": "北京百川百智科贸有限公司",
    "发货地": "北京市丰台区",
    "发货履约率": "/",
    "回头率": "0%",
    "客服响应率": "96.0%",
    "工厂年限": "12年",
    "源头厂家": "/",
    "综合服务分": "4.5",
    "评价数": "21条有内容1条",
    "起订量": "1",
    "近 14 天销量": "/",
    "近 90 天销量": "/",
    "首次上架时间": "2016/10/17",
    "48h 揽收率": "/"
  },
  {
    "商品名称": "Oxalic Acid Cleaner Tile Toilet Powerful Descaler Exterior Wall Alkali Return High Concentration Solution Industrial Cement Cleaning Agent",
    "商品图链接": "https://cbu01.alicdn.com/O1CN01H5igHQ1o8x4IGOXeo_!!2213065335181-0-cib.jpg",
    "价格": "¥70.00",
    "供应商名称": "山东霸克生物科技有限公司",
    "发货地": "山东 滨州市",
    "发货履约率": "/",
    "回头率": "0%",
    "客服响应率": "88.0%",
    "工厂年限": "5年",
    "源头厂家": "/",
    "综合服务分": "4.0",
    "评价数": "/",
    "起订量": "1",
    "近 14 天销量": "/",
    "近 90 天销量": "/",
    "首次上架时间": "2025/04/25",
    "48h 揽收率": "/"
  },
  {
    "商品名称": "German Autosol Metal Polishing Paste Copper Polishing Paste Scratch Removal Copper Rust Repair Hardware Stainless Steel Polishing Paste 100",
    "商品图链接": "https://cbu01.alicdn.com/O1CN01AvDKMN1XMpZU655rW_!!2207442910.png",
    "价格": "¥16.10",
    "供应商名称": "杭州建德凯俜五金商行(个体工商户)",
    "发货地": "浙江 杭州市",
    "发货履约率": "/",
    "回头率": "0%",
    "客服响应率": "81.0%",
    "工厂年限": "1年",
    "源头厂家": "/",
    "综合服务分": "3.5",
    "评价数": "/",
    "起订量": "1",
    "近 14 天销量": "/",
    "近 90 天销量": "/",
    "首次上架时间": "2025/08/31",
    "48h 揽收率": "/"
  },
  {
    "商品名称": "Odesu Fully Bright Glass Water Removes Oil Film, Removes Dirt and Removes Water Marks",
    "商品图链接": "https://cbu01.alicdn.com/O1CN01RdjPg01pmczLywePN_!!3915605403-0-cib.jpg",
    "价格": "¥13.50",
    "供应商名称": "江门市蓬江区丽晶抛光材料总汇",
    "发货地": "广东 江门市",
    "发货履约率": "/",
    "回头率": "0%",
    "客服响应率": "0.0%",
    "工厂年限": "8年",
    "源头厂家": "/",
    "综合服务分": "3.5",
    "评价数": "/",
    "起订量": "1",
    "近 14 天销量": "/",
    "近 90 天销量": "/",
    "首次上架时间": "2025/04/03",
    "48h 揽收率": "/"
  }
]
